oagdedupe/__init__.py
oagdedupe/_typing.py
oagdedupe/api.py
oagdedupe/base.py
oagdedupe/block/__init__.py
oagdedupe/block/base.py
oagdedupe/block/blocking.py
oagdedupe/block/forward.py
oagdedupe/block/learner.py
oagdedupe/block/mixin.py
oagdedupe/block/optimizers.py
oagdedupe/block/pairs.py
oagdedupe/block/schemes.py
oagdedupe/cluster/__init__.py
oagdedupe/cluster/cluster.py
oagdedupe/containers.py
oagdedupe/db/__init__.py
oagdedupe/db/initialize.py
oagdedupe/db/orm.py
oagdedupe/db/tables.py
oagdedupe/distance/__init__.py
oagdedupe/distance/string.py
oagdedupe/fastapi/__init__.py
oagdedupe/fastapi/fapi.py
oagdedupe/fastapi/main.py
oagdedupe/labelstudio/__init__.py
oagdedupe/labelstudio/lsapi.py
oagdedupe/postgres/Dockerfile
oagdedupe/postgres/funcs.py
oagdedupe/settings.py
oagdedupe/utils.py
oagdedupe-0.2.1.dist-info/WHEEL
oagdedupe-0.2.1.dist-info/METADATA
oagdedupe-0.2.1.dist-info/RECORD
